{
  "creator": "绘世TONY",
  "slug": "full-time-awakening",
  "title": "Full-Time Awakening",
  "title_indonesian": "全职觉醒",
  "image": "http://kacu.gmbr.pro/uploads/manga-images/f/full-time-awakening/thumbnail.jpg",
  "synopsis": "Sebagai kapten Legiun Divine dan Awakener terkuat, Bai Yi dikhianati oleh seorang kawan, menyaksikan semua rekan satu timnya mati di depan matanya. Baru setelah itu dia menyadari bahwa dia selalu menjadi pion dari mereka yang berkuasa. Setelah kehilangan segalanya, dia terlahir kembali 20 tahun yang lalu, kembali ke masa sekolah menengahnya sebelum terbangun. Saat itu, keluarga dan rekan satu timnya masih hidup. Untuk menyelamatkan mereka, untuk membalaskan dendam pengkhianat, dan untuk menggulingkan seluruh sistem pemerintahan yang korup, ia memulai jalan kekuatan yang sepi.",
  "synopsis_full": "Sebagai kapten Legiun Divine dan Awakener terkuat, Bai Yi dikhianati oleh seorang kawan, menyaksikan semua rekan satu timnya mati di depan matanya. Baru setelah itu dia menyadari bahwa dia selalu menjadi pion dari mereka yang berkuasa. Setelah kehilangan segalanya, dia terlahir kembali 20 tahun yang lalu, kembali ke masa sekolah menengahnya sebelum terbangun. Saat itu, keluarga dan rekan satu timnya masih hidup. Untuk menyelamatkan mereka, untuk membalaskan dendam pengkhianat, dan untuk menggulingkan seluruh sistem pemerintahan yang korup, ia memulai jalan kekuatan yang sepi.",
  "summary": "Sebagai kapten Legiun Divine dan Awakener terkuat, Bai Yi dikhianati oleh seorang kawan, menyaksikan semua rekan satu timnya mati di depan matanya. Baru setelah itu dia menyadari bahwa dia selalu menjadi pion dari mereka yang berkuasa. Setelah kehilangan segalanya, dia terlahir kembali 20 tahun yang lalu, kembali ke masa sekolah menengahnya sebelum terbangun. Saat itu, keluarga dan rekan satu timnya masih hidup. Untuk menyelamatkan mereka, untuk membalaskan dendam pengkhianat, dan untuk menggulingkan seluruh sistem pemerintahan yang korup, ia memulai jalan kekuatan yang sepi.",
  "background_story": "",
  "metadata": {
    "type": "Manhua",
    "author": "绘世TONY",
    "status": "Ongoing",
    "concept": "",
    "age_rating": "",
    "reading_direction": "vertical"
  },
  "genres": [
    {
      "name": "Action",
      "slug": "action",
      "link": "#"
    },
    {
      "name": "Fantasy",
      "slug": "fantasy",
      "link": "#"
    }
  ],
  "chapters": [
    {
      "chapter": "Chapter 53",
      "slug": "full-time-awakening-chapter-53",
      "link": "https://www.manhwaindo.my/full-time-awakening-chapter-53/",
      "date": "27 Maret 2026"
    },
    {
      "chapter": "Chapter 52",
      "slug": "full-time-awakening-chapter-52",
      "link": "https://www.manhwaindo.my/full-time-awakening-chapter-52/",
      "date": "27 Maret 2026"
    },
    {
      "chapter": "Chapter 51",
      "slug": "full-time-awakening-chapter-51",
      "link": "https://www.manhwaindo.my/full-time-awakening-chapter-51/",
      "date": "25 Maret 2026"
    },
    {
      "chapter": "Chapter 50",
      "slug": "full-time-awakening-chapter-50",
      "link": "https://www.manhwaindo.my/full-time-awakening-chapter-50/",
      "date": "25 Maret 2026"
    },
    {
      "chapter": "Chapter 49",
      "slug": "full-time-awakening-chapter-49",
      "link": "https://www.manhwaindo.my/full-time-awakening-chapter-49/",
      "date": "19 Maret 2026"
    },
    {
      "chapter": "Chapter 48",
      "slug": "full-time-awakening-chapter-48",
      "link": "https://www.manhwaindo.my/full-time-awakening-chapter-48/",
      "date": "19 Maret 2026"
    },
    {
      "chapter": "Chapter 47",
      "slug": "full-time-awakening-chapter-47",
      "link": "https://www.manhwaindo.my/full-time-awakening-chapter-47/",
      "date": "17 Maret 2026"
    },
    {
      "chapter": "Chapter 46",
      "slug": "full-time-awakening-chapter-46",
      "link": "https://www.manhwaindo.my/full-time-awakening-chapter-46/",
      "date": "17 Maret 2026"
    },
    {
      "chapter": "Chapter 45",
      "slug": "full-time-awakening-chapter-45",
      "link": "https://www.manhwaindo.my/full-time-awakening-chapter-45/",
      "date": "15 Maret 2026"
    },
    {
      "chapter": "Chapter 44",
      "slug": "full-time-awakening-chapter-44",
      "link": "https://www.manhwaindo.my/full-time-awakening-chapter-44/",
      "date": "15 Maret 2026"
    },
    {
      "chapter": "Chapter 43",
      "slug": "full-time-awakening-chapter-43",
      "link": "https://www.manhwaindo.my/full-time-awakening-chapter-43/",
      "date": "13 Maret 2026"
    },
    {
      "chapter": "Chapter 42",
      "slug": "full-time-awakening-chapter-42",
      "link": "https://www.manhwaindo.my/full-time-awakening-chapter-42/",
      "date": "13 Maret 2026"
    },
    {
      "chapter": "Chapter 41",
      "slug": "full-time-awakening-chapter-41",
      "link": "https://www.manhwaindo.my/full-time-awakening-chapter-41/",
      "date": "12 Maret 2026"
    },
    {
      "chapter": "Chapter 40",
      "slug": "full-time-awakening-chapter-40",
      "link": "https://www.manhwaindo.my/full-time-awakening-chapter-40/",
      "date": "12 Maret 2026"
    },
    {
      "chapter": "Chapter 39",
      "slug": "full-time-awakening-chapter-39",
      "link": "https://www.manhwaindo.my/full-time-awakening-chapter-39/",
      "date": "10 Maret 2026"
    },
    {
      "chapter": "Chapter 38",
      "slug": "full-time-awakening-chapter-38",
      "link": "https://www.manhwaindo.my/full-time-awakening-chapter-38/",
      "date": "10 Maret 2026"
    },
    {
      "chapter": "Chapter 37",
      "slug": "full-time-awakening-chapter-37",
      "link": "https://www.manhwaindo.my/full-time-awakening-chapter-37/",
      "date": "8 Maret 2026"
    },
    {
      "chapter": "Chapter 36",
      "slug": "full-time-awakening-chapter-36",
      "link": "https://www.manhwaindo.my/full-time-awakening-chapter-36/",
      "date": "8 Maret 2026"
    },
    {
      "chapter": "Chapter 35",
      "slug": "full-time-awakening-chapter-35",
      "link": "https://www.manhwaindo.my/full-time-awakening-chapter-35/",
      "date": "5 Maret 2026"
    },
    {
      "chapter": "Chapter 34",
      "slug": "full-time-awakening-chapter-34",
      "link": "https://www.manhwaindo.my/full-time-awakening-chapter-34/",
      "date": "5 Maret 2026"
    },
    {
      "chapter": "Chapter 33",
      "slug": "full-time-awakening-chapter-33",
      "link": "https://www.manhwaindo.my/full-time-awakening-chapter-33/",
      "date": "4 Maret 2026"
    },
    {
      "chapter": "Chapter 32",
      "slug": "full-time-awakening-chapter-32",
      "link": "https://www.manhwaindo.my/full-time-awakening-chapter-32/",
      "date": "4 Maret 2026"
    },
    {
      "chapter": "Chapter 31",
      "slug": "full-time-awakening-chapter-31",
      "link": "https://www.manhwaindo.my/full-time-awakening-chapter-31/",
      "date": "2 Maret 2026"
    },
    {
      "chapter": "Chapter 30",
      "slug": "full-time-awakening-chapter-30",
      "link": "https://www.manhwaindo.my/full-time-awakening-chapter-30/",
      "date": "2 Maret 2026"
    },
    {
      "chapter": "Chapter 29",
      "slug": "full-time-awakening-chapter-29",
      "link": "https://www.manhwaindo.my/full-time-awakening-chapter-29/",
      "date": "28 Februari 2026"
    },
    {
      "chapter": "Chapter 28",
      "slug": "full-time-awakening-chapter-28",
      "link": "https://www.manhwaindo.my/full-time-awakening-chapter-28/",
      "date": "28 Februari 2026"
    },
    {
      "chapter": "Chapter 27",
      "slug": "full-time-awakening-chapter-27",
      "link": "https://www.manhwaindo.my/full-time-awakening-chapter-27/",
      "date": "26 Februari 2026"
    },
    {
      "chapter": "Chapter 26",
      "slug": "full-time-awakening-chapter-26",
      "link": "https://www.manhwaindo.my/full-time-awakening-chapter-26/",
      "date": "26 Februari 2026"
    },
    {
      "chapter": "Chapter 25",
      "slug": "full-time-awakening-chapter-25",
      "link": "https://www.manhwaindo.my/full-time-awakening-chapter-25/",
      "date": "25 Februari 2026"
    },
    {
      "chapter": "Chapter 24",
      "slug": "full-time-awakening-chapter-24",
      "link": "https://www.manhwaindo.my/full-time-awakening-chapter-24/",
      "date": "25 Februari 2026"
    },
    {
      "chapter": "Chapter 23",
      "slug": "full-time-awakening-chapter-23",
      "link": "https://www.manhwaindo.my/full-time-awakening-chapter-23/",
      "date": "24 Februari 2026"
    },
    {
      "chapter": "Chapter 22",
      "slug": "full-time-awakening-chapter-22",
      "link": "https://www.manhwaindo.my/full-time-awakening-chapter-22/",
      "date": "24 Februari 2026"
    },
    {
      "chapter": "Chapter 21",
      "slug": "full-time-awakening-chapter-21",
      "link": "https://www.manhwaindo.my/full-time-awakening-chapter-21/",
      "date": "24 Februari 2026"
    },
    {
      "chapter": "Chapter 20",
      "slug": "full-time-awakening-chapter-20",
      "link": "https://www.manhwaindo.my/full-time-awakening-chapter-20/",
      "date": "24 Februari 2026"
    },
    {
      "chapter": "Chapter 19",
      "slug": "full-time-awakening-chapter-19",
      "link": "https://www.manhwaindo.my/full-time-awakening-chapter-19/",
      "date": "24 Februari 2026"
    },
    {
      "chapter": "Chapter 18",
      "slug": "full-time-awakening-chapter-18",
      "link": "https://www.manhwaindo.my/full-time-awakening-chapter-18/",
      "date": "24 Februari 2026"
    },
    {
      "chapter": "Chapter 17",
      "slug": "full-time-awakening-chapter-17",
      "link": "https://www.manhwaindo.my/full-time-awakening-chapter-17/",
      "date": "5 Desember 2025"
    },
    {
      "chapter": "Chapter 16",
      "slug": "full-time-awakening-chapter-16",
      "link": "https://www.manhwaindo.my/full-time-awakening-chapter-16/",
      "date": "5 Desember 2025"
    },
    {
      "chapter": "Chapter 15",
      "slug": "full-time-awakening-chapter-15",
      "link": "https://www.manhwaindo.my/full-time-awakening-chapter-15/",
      "date": "5 Desember 2025"
    },
    {
      "chapter": "Chapter 14",
      "slug": "full-time-awakening-chapter-14",
      "link": "https://www.manhwaindo.my/full-time-awakening-chapter-14/",
      "date": "5 Desember 2025"
    },
    {
      "chapter": "Chapter 13",
      "slug": "full-time-awakening-chapter-13",
      "link": "https://www.manhwaindo.my/full-time-awakening-chapter-13/",
      "date": "5 Desember 2025"
    },
    {
      "chapter": "Chapter 12",
      "slug": "full-time-awakening-chapter-12",
      "link": "https://www.manhwaindo.my/full-time-awakening-chapter-12/",
      "date": "5 Desember 2025"
    },
    {
      "chapter": "Chapter 11",
      "slug": "full-time-awakening-chapter-11",
      "link": "https://www.manhwaindo.my/full-time-awakening-chapter-11/",
      "date": "5 Desember 2025"
    },
    {
      "chapter": "Chapter 10",
      "slug": "full-time-awakening-chapter-10",
      "link": "https://www.manhwaindo.my/full-time-awakening-chapter-10/",
      "date": "5 Desember 2025"
    },
    {
      "chapter": "Chapter 09",
      "slug": "full-time-awakening-chapter-09",
      "link": "https://www.manhwaindo.my/full-time-awakening-chapter-09/",
      "date": "5 Desember 2025"
    },
    {
      "chapter": "Chapter 08",
      "slug": "full-time-awakening-chapter-08",
      "link": "https://www.manhwaindo.my/full-time-awakening-chapter-08/",
      "date": "5 Desember 2025"
    },
    {
      "chapter": "Chapter 07",
      "slug": "full-time-awakening-chapter-07",
      "link": "https://www.manhwaindo.my/full-time-awakening-chapter-07/",
      "date": "5 Desember 2025"
    },
    {
      "chapter": "Chapter 06",
      "slug": "full-time-awakening-chapter-06",
      "link": "https://www.manhwaindo.my/full-time-awakening-chapter-06/",
      "date": "5 Desember 2025"
    },
    {
      "chapter": "Chapter 05",
      "slug": "full-time-awakening-chapter-05",
      "link": "https://www.manhwaindo.my/full-time-awakening-chapter-05/",
      "date": "5 Desember 2025"
    },
    {
      "chapter": "Chapter 04",
      "slug": "full-time-awakening-chapter-04",
      "link": "https://www.manhwaindo.my/full-time-awakening-chapter-04/",
      "date": "5 Desember 2025"
    },
    {
      "chapter": "Chapter 03",
      "slug": "full-time-awakening-chapter-03",
      "link": "https://www.manhwaindo.my/full-time-awakening-chapter-03/",
      "date": "5 Desember 2025"
    },
    {
      "chapter": "Chapter 02",
      "slug": "full-time-awakening-chapter-02",
      "link": "https://www.manhwaindo.my/full-time-awakening-chapter-02/",
      "date": "5 Desember 2025"
    },
    {
      "chapter": "Chapter 01",
      "slug": "full-time-awakening-chapter-01",
      "link": "https://www.manhwaindo.my/full-time-awakening-chapter-01/",
      "date": "5 Desember 2025"
    }
  ],
  "similar_manga": []
}
